AUTHORS.rst
CONTRIBUTING.rst
HISTORY.rst
LICENSE
MANIFEST.in
README.rst
setup.cfg
setup.py
browserstack_tools/__init__.py
browserstack_tools/models.py
browserstack_tools/testcases.py
browserstack_tools/contrib/BrowserStackLocal
browserstack_tools/static/js/browserstack_tools.js
browserstack_tools/templates/browserstack_tools/base.html
django_browserstack_tools.egg-info/PKG-INFO
django_browserstack_tools.egg-info/SOURCES.txt
django_browserstack_tools.egg-info/dependency_links.txt
django_browserstack_tools.egg-info/not-zip-safe
django_browserstack_tools.egg-info/top_level.txt