Metadata-Version: 1.1
Name: django-browserstack-tools
Version: 0.1.1
Summary: Unofficial Browserstack integration for Django
Home-page: https://github.com/qdqmedia/django-browserstack-tools
Author: QDQ media S.A.U.
Author-email: tecnologia@qdqmedia.com
License: BSD
Keywords: django-browserstack-tools
Platform: UNKNOWN
Classifier: Development Status :: 2 - Pre-Alpha
Classifier: Framework :: Django
Classifier: Intended Audience :: Developers
Classifier: License :: OSI Approved :: BSD License
Classifier: Natural Language :: English
Classifier: Programming Language :: Python :: 2
Classifier: Programming Language :: Python :: 2.6
Classifier: Programming Language :: Python :: 2.7
Classifier: Programming Language :: Python :: 3
Classifier: Programming Language :: Python :: 3.3
